markmymedia/__init__.py
markmymedia/__main__.py
markmymedia/cli.py
markmymedia/errors.py
markmymedia/mark_audio.py
markmymedia/mark_image.py
markmymedia/mark_video.py
markmymedia/utils.py
markmymedia-1.0.0.dist-info/licenses/LICENSE
markmymedia-1.0.0.dist-info/METADATA
markmymedia-1.0.0.dist-info/WHEEL
markmymedia-1.0.0.dist-info/entry_points.txt
markmymedia-1.0.0.dist-info/top_level.txt
markmymedia-1.0.0.dist-info/RECORD
