Metadata-Version: 2.4
Name: MarkMyMedia
Version: 1.0.0
Summary: A fast, simple utility to visually stamp media files with their filenames, preparing them for multimodal LLM training and analysis.
Author-email: laVashik <me@lavashik.dev>
License: MIT
Project-URL: Homepage, https://github.com/LaVashikk/MarkMyMedia-LLM
Project-URL: Bug Tracker, https://github.com/IaVashik/MarkMyMedia-LLM/issues
Keywords: multimodal,llm,ffmpeg,media,image-processing,video-processing,audio-processing,utilities
Classifier: Programming Language :: Python :: 3
Classifier: Programming Language :: Python :: 3.8
Classifier: Programming Language :: Python :: 3.9
Classifier: Programming Language :: Python :: 3.10
Classifier: Programming Language :: Python :: 3.11
Classifier: License :: OSI Approved :: MIT License
Classifier: Operating System :: OS Independent
Classifier: Topic :: Multimedia :: Video
Classifier: Topic :: Multimedia :: Graphics
Classifier: Topic :: Multimedia :: Sound/Audio
Classifier: Topic :: Scientific/Engineering :: Artificial Intelligence
Classifier: Topic :: Utilities
Classifier: Environment :: Console
Classifier: Intended Audience :: Developers
Classifier: Intended Audience :: Science/Research
Requires-Python: >=3.8
License-File: LICENSE
Requires-Dist: Pillow
Dynamic: license-file
